{
  "total": 28,
  "rows": [
    {
      "name": "纪委监督",
      "score11": 10,
      "score12": 10,
      "score21": 10,
      "score22": 10,
      "score31": 10,
      "score32": 10,
      "score41": 10,
      "score42": 10,
      "score51": 10,
      "score52": 10,
      "score61": 10,
      "score62": 10,
      "score71": 10,
      "score72": 10,
      "score81": 10,
      "score82": 10,
      "score91": 10,
      "score92": 10,
      "score101": 10,
      "score102": 10,
      "score111": 10,
      "score112": 10,
      "score121": 10,
      "score122": 10,
      "score131": 10,
      "score132": 10,
      "score141": 10,
      "score142": 10,
      "score151": 10,
      "score152": 10,
      "score161": 10,
      "score162": 10,
      "score171": 10,
      "score172": 10,
      "score181": 10,
      "score182": 10,
      "score191": 10,
      "score192": 10,
      "score201": 190,
      "score202": 190
    },
    {
      "name": "监督1",
      "score11": 10,
      "score12": 10,
      "score21": 10,
      "score22": 10,
      "score31": 10,
      "score32": 10,
      "score41": 10,
      "score42": 10,
      "score51": 10,
      "score52": 10,
      "score61": 10,
      "score62": 10,
      "score71": 10,
      "score72": 10,
      "score81": 10,
      "score82": 10,
      "score91": 10,
      "score92": 10,
      "score101": 10,
      "score102": 10,
      "score111": 10,
      "score112": 10,
      "score121": 10,
      "score122": 10,
      "score131": 10,
      "score132": 10,
      "score141": 10,
      "score142": 10,
      "score151": 10,
      "score152": 10,
      "score161": 10,
      "score162": 10,
      "score171": 10,
      "score172": 10,
      "score181": 10,
      "score182": 10,
      "score191": 10,
      "score192": 10,
      "score201": 190,
      "score202": 190
    },
    {
      "name": "监督2",
      "score11": 10,
      "score12": 10,
      "score21": 10,
      "score22": 10,
      "score31": 10,
      "score32": 10,
      "score41": 10,
      "score42": 10,
      "score51": 10,
      "score52": 10,
      "score61": 10,
      "score62": 10,
      "score71": 10,
      "score72": 10,
      "score81": 10,
      "score82": 10,
      "score91": 10,
      "score92": 10,
      "score101": 10,
      "score102": 10,
      "score111": 10,
      "score112": 10,
      "score121": 10,
      "score122": 10,
      "score131": 10,
      "score132": 10,
      "score141": 10,
      "score142": 10,
      "score151": 10,
      "score152": 10,
      "score161": 10,
      "score162": 10,
      "score171": 10,
      "score172": 10,
      "score181": 10,
      "score182": 10,
      "score191": 10,
      "score192": 10,
      "score201": 190,
      "score202": 190
    },
    {
      "name": "监督3",
      "score11": 10,
      "score12": 10,
      "score21": 10,
      "score22": 10,
      "score31": 10,
      "score32": 10,
      "score41": 10,
      "score42": 10,
      "score51": 10,
      "score52": 10,
      "score61": 10,
      "score62": 10,
      "score71": 10,
      "score72": 10,
      "score81": 10,
      "score82": 10,
      "score91": 10,
      "score92": 10,
      "score101": 10,
      "score102": 10,
      "score111": 10,
      "score112": 10,
      "score121": 10,
      "score122": 10,
      "score131": 10,
      "score132": 10,
      "score141": 10,
      "score142": 10,
      "score151": 10,
      "score152": 10,
      "score161": 10,
      "score162": 10,
      "score171": 10,
      "score172": 10,
      "score181": 10,
      "score182": 10,
      "score191": 10,
      "score192": 10,
      "score201": 190,
      "score202": 190
    },
    {
      "name": "监督4",
      "score11": 10,
      "score12": 10,
      "score21": 10,
      "score22": 10,
      "score31": 10,
      "score32": 10,
      "score41": 10,
      "score42": 10,
      "score51": 10,
      "score52": 10,
      "score61": 10,
      "score62": 10,
      "score71": 10,
      "score72": 10,
      "score81": 10,
      "score82": 10,
      "score91": 10,
      "score92": 10,
      "score101": 10,
      "score102": 10,
      "score111": 10,
      "score112": 10,
      "score121": 10,
      "score122": 10,
      "score131": 10,
      "score132": 10,
      "score141": 10,
      "score142": 10,
      "score151": 10,
      "score152": 10,
      "score161": 10,
      "score162": 10,
      "score171": 10,
      "score172": 10,
      "score181": 10,
      "score182": 10,
      "score191": 10,
      "score192": 10,
      "score201": 190,
      "score202": 190
    },
    {
      "name": "监督5",
      "score11": 10,
      "score12": 10,
      "score21": 10,
      "score22": 10,
      "score31": 10,
      "score32": 10,
      "score41": 10,
      "score42": 10,
      "score51": 10,
      "score52": 10,
      "score61": 10,
      "score62": 10,
      "score71": 10,
      "score72": 10,
      "score81": 10,
      "score82": 10,
      "score91": 10,
      "score92": 10,
      "score101": 10,
      "score102": 10,
      "score111": 10,
      "score112": 10,
      "score121": 10,
      "score122": 10,
      "score131": 10,
      "score132": 10,
      "score141": 10,
      "score142": 10,
      "score151": 10,
      "score152": 10,
      "score161": 10,
      "score162": 10,
      "score171": 10,
      "score172": 10,
      "score181": 10,
      "score182": 10,
      "score191": 10,
      "score192": 10,
      "score201": 190,
      "score202": 190
    },
    {
      "name": "监督6",
      "score11": 10,
      "score12": 10,
      "score21": 10,
      "score22": 10,
      "score31": 10,
      "score32": 10,
      "score41": 10,
      "score42": 10,
      "score51": 10,
      "score52": 10,
      "score61": 10,
      "score62": 10,
      "score71": 10,
      "score72": 10,
      "score81": 10,
      "score82": 10,
      "score91": 10,
      "score92": 10,
      "score101": 10,
      "score102": 10,
      "score111": 10,
      "score112": 10,
      "score121": 10,
      "score122": 10,
      "score131": 10,
      "score132": 10,
      "score141": 10,
      "score142": 10,
      "score151": 10,
      "score152": 10,
      "score161": 10,
      "score162": 10,
      "score171": 10,
      "score172": 10,
      "score181": 10,
      "score182": 10,
      "score191": 10,
      "score192": 10,
      "score201": 190,
      "score202": 190
    },
    {
      "name": "监督7",
      "score11": 10,
      "score12": 10,
      "score21": 10,
      "score22": 10,
      "score31": 10,
      "score32": 10,
      "score41": 10,
      "score42": 10,
      "score51": 10,
      "score52": 10,
      "score61": 10,
      "score62": 10,
      "score71": 10,
      "score72": 10,
      "score81": 10,
      "score82": 10,
      "score91": 10,
      "score92": 10,
      "score101": 10,
      "score102": 10,
      "score111": 10,
      "score112": 10,
      "score121": 10,
      "score122": 10,
      "score131": 10,
      "score132": 10,
      "score141": 10,
      "score142": 10,
      "score151": 10,
      "score152": 10,
      "score161": 10,
      "score162": 10,
      "score171": 10,
      "score172": 10,
      "score181": 10,
      "score182": 10,
      "score191": 10,
      "score192": 10,
      "score201": 190,
      "score202": 190
    },
    {
      "name": "监督8",
      "score11": 10,
      "score12": 10,
      "score21": 10,
      "score22": 10,
      "score31": 10,
      "score32": 10,
      "score41": 10,
      "score42": 10,
      "score51": 10,
      "score52": 10,
      "score61": 10,
      "score62": 10,
      "score71": 10,
      "score72": 10,
      "score81": 10,
      "score82": 10,
      "score91": 10,
      "score92": 10,
      "score101": 10,
      "score102": 10,
      "score111": 10,
      "score112": 10,
      "score121": 10,
      "score122": 10,
      "score131": 10,
      "score132": 10,
      "score141": 10,
      "score142": 10,
      "score151": 10,
      "score152": 10,
      "score161": 10,
      "score162": 10,
      "score171": 10,
      "score172": 10,
      "score181": 10,
      "score182": 10,
      "score191": 10,
      "score192": 10,
      "score201": 190,
      "score202": 190
    },
    {
      "name": "监督9",
      "score11": 10,
      "score12": 10,
      "score21": 10,
      "score22": 10,
      "score31": 10,
      "score32": 10,
      "score41": 10,
      "score42": 10,
      "score51": 10,
      "score52": 10,
      "score61": 10,
      "score62": 10,
      "score71": 10,
      "score72": 10,
      "score81": 10,
      "score82": 10,
      "score91": 10,
      "score92": 10,
      "score101": 10,
      "score102": 10,
      "score111": 10,
      "score112": 10,
      "score121": 10,
      "score122": 10,
      "score131": 10,
      "score132": 10,
      "score141": 10,
      "score142": 10,
      "score151": 10,
      "score152": 10,
      "score161": 10,
      "score162": 10,
      "score171": 10,
      "score172": 10,
      "score181": 10,
      "score182": 10,
      "score191": 10,
      "score192": 10,
      "score201": 190,
      "score202": 190
    },
    {
      "name": "监督10",
      "score11": 10,
      "score12": 10,
      "score21": 10,
      "score22": 10,
      "score31": 10,
      "score32": 10,
      "score41": 10,
      "score42": 10,
      "score51": 10,
      "score52": 10,
      "score61": 10,
      "score62": 10,
      "score71": 10,
      "score72": 10,
      "score81": 10,
      "score82": 10,
      "score91": 10,
      "score92": 10,
      "score101": 10,
      "score102": 10,
      "score111": 10,
      "score112": 10,
      "score121": 10,
      "score122": 10,
      "score131": 10,
      "score132": 10,
      "score141": 10,
      "score142": 10,
      "score151": 10,
      "score152": 10,
      "score161": 10,
      "score162": 10,
      "score171": 10,
      "score172": 10,
      "score181": 10,
      "score182": 10,
      "score191": 10,
      "score192": 10,
      "score201": 190,
      "score202": 190
    },
    {
      "name": "监督11",
      "score11": 10,
      "score12": 10,
      "score21": 10,
      "score22": 10,
      "score31": 10,
      "score32": 10,
      "score41": 10,
      "score42": 10,
      "score51": 10,
      "score52": 10,
      "score61": 10,
      "score62": 10,
      "score71": 10,
      "score72": 10,
      "score81": 10,
      "score82": 10,
      "score91": 10,
      "score92": 10,
      "score101": 10,
      "score102": 10,
      "score111": 10,
      "score112": 10,
      "score121": 10,
      "score122": 10,
      "score131": 10,
      "score132": 10,
      "score141": 10,
      "score142": 10,
      "score151": 10,
      "score152": 10,
      "score161": 10,
      "score162": 10,
      "score171": 10,
      "score172": 10,
      "score181": 10,
      "score182": 10,
      "score191": 10,
      "score192": 10,
      "score201": 190,
      "score202": 190
    },
    {
      "name": "监督12",
      "score11": 10,
      "score12": 10,
      "score21": 10,
      "score22": 10,
      "score31": 10,
      "score32": 10,
      "score41": 10,
      "score42": 10,
      "score51": 10,
      "score52": 10,
      "score61": 10,
      "score62": 10,
      "score71": 10,
      "score72": 10,
      "score81": 10,
      "score82": 10,
      "score91": 10,
      "score92": 10,
      "score101": 10,
      "score102": 10,
      "score111": 10,
      "score112": 10,
      "score121": 10,
      "score122": 10,
      "score131": 10,
      "score132": 10,
      "score141": 10,
      "score142": 10,
      "score151": 10,
      "score152": 10,
      "score161": 10,
      "score162": 10,
      "score171": 10,
      "score172": 10,
      "score181": 10,
      "score182": 10,
      "score191": 10,
      "score192": 10,
      "score201": 190,
      "score202": 190
    },
    {
      "name": "监督13",
      "score11": 10,
      "score12": 10,
      "score21": 10,
      "score22": 10,
      "score31": 10,
      "score32": 10,
      "score41": 10,
      "score42": 10,
      "score51": 10,
      "score52": 10,
      "score61": 10,
      "score62": 10,
      "score71": 10,
      "score72": 10,
      "score81": 10,
      "score82": 10,
      "score91": 10,
      "score92": 10,
      "score101": 10,
      "score102": 10,
      "score111": 10,
      "score112": 10,
      "score121": 10,
      "score122": 10,
      "score131": 10,
      "score132": 10,
      "score141": 10,
      "score142": 10,
      "score151": 10,
      "score152": 10,
      "score161": 10,
      "score162": 10,
      "score171": 10,
      "score172": 10,
      "score181": 10,
      "score182": 10,
      "score191": 10,
      "score192": 10,
      "score201": 190,
      "score202": 190
    },
    {
      "name": "监督14",
      "score11": 10,
      "score12": 10,
      "score21": 10,
      "score22": 10,
      "score31": 10,
      "score32": 10,
      "score41": 10,
      "score42": 10,
      "score51": 10,
      "score52": 10,
      "score61": 10,
      "score62": 10,
      "score71": 10,
      "score72": 10,
      "score81": 10,
      "score82": 10,
      "score91": 10,
      "score92": 10,
      "score101": 10,
      "score102": 10,
      "score111": 10,
      "score112": 10,
      "score121": 10,
      "score122": 10,
      "score131": 10,
      "score132": 10,
      "score141": 10,
      "score142": 10,
      "score151": 10,
      "score152": 10,
      "score161": 10,
      "score162": 10,
      "score171": 10,
      "score172": 10,
      "score181": 10,
      "score182": 10,
      "score191": 10,
      "score192": 10,
      "score201": 190,
      "score202": 190
    },
    {
      "name": "监督15",
      "score11": 10,
      "score12": 10,
      "score21": 10,
      "score22": 10,
      "score31": 10,
      "score32": 10,
      "score41": 10,
      "score42": 10,
      "score51": 10,
      "score52": 10,
      "score61": 10,
      "score62": 10,
      "score71": 10,
      "score72": 10,
      "score81": 10,
      "score82": 10,
      "score91": 10,
      "score92": 10,
      "score101": 10,
      "score102": 10,
      "score111": 10,
      "score112": 10,
      "score121": 10,
      "score122": 10,
      "score131": 10,
      "score132": 10,
      "score141": 10,
      "score142": 10,
      "score151": 10,
      "score152": 10,
      "score161": 10,
      "score162": 10,
      "score171": 10,
      "score172": 10,
      "score181": 10,
      "score182": 10,
      "score191": 10,
      "score192": 10,
      "score201": 190,
      "score202": 190
    },
    {
      "name": "监督16",
      "score11": 10,
      "score12": 10,
      "score21": 10,
      "score22": 10,
      "score31": 10,
      "score32": 10,
      "score41": 10,
      "score42": 10,
      "score51": 10,
      "score52": 10,
      "score61": 10,
      "score62": 10,
      "score71": 10,
      "score72": 10,
      "score81": 10,
      "score82": 10,
      "score91": 10,
      "score92": 10,
      "score101": 10,
      "score102": 10,
      "score111": 10,
      "score112": 10,
      "score121": 10,
      "score122": 10,
      "score131": 10,
      "score132": 10,
      "score141": 10,
      "score142": 10,
      "score151": 10,
      "score152": 10,
      "score161": 10,
      "score162": 10,
      "score171": 10,
      "score172": 10,
      "score181": 10,
      "score182": 10,
      "score191": 10,
      "score192": 10,
      "score201": 190,
      "score202": 190
    },
    {
      "name": "监督17",
      "score11": 10,
      "score12": 10,
      "score21": 10,
      "score22": 10,
      "score31": 10,
      "score32": 10,
      "score41": 10,
      "score42": 10,
      "score51": 10,
      "score52": 10,
      "score61": 10,
      "score62": 10,
      "score71": 10,
      "score72": 10,
      "score81": 10,
      "score82": 10,
      "score91": 10,
      "score92": 10,
      "score101": 10,
      "score102": 10,
      "score111": 10,
      "score112": 10,
      "score121": 10,
      "score122": 10,
      "score131": 10,
      "score132": 10,
      "score141": 10,
      "score142": 10,
      "score151": 10,
      "score152": 10,
      "score161": 10,
      "score162": 10,
      "score171": 10,
      "score172": 10,
      "score181": 10,
      "score182": 10,
      "score191": 10,
      "score192": 10,
      "score201": 190,
      "score202": 190
    },
    {
      "name": "监督18",
      "score11": 10,
      "score12": 10,
      "score21": 10,
      "score22": 10,
      "score31": 10,
      "score32": 10,
      "score41": 10,
      "score42": 10,
      "score51": 10,
      "score52": 10,
      "score61": 10,
      "score62": 10,
      "score71": 10,
      "score72": 10,
      "score81": 10,
      "score82": 10,
      "score91": 10,
      "score92": 10,
      "score101": 10,
      "score102": 10,
      "score111": 10,
      "score112": 10,
      "score121": 10,
      "score122": 10,
      "score131": 10,
      "score132": 10,
      "score141": 10,
      "score142": 10,
      "score151": 10,
      "score152": 10,
      "score161": 10,
      "score162": 10,
      "score171": 10,
      "score172": 10,
      "score181": 10,
      "score182": 10,
      "score191": 10,
      "score192": 10,
      "score201": 190,
      "score202": 190
    },
    {
      "name": "监督19",
      "score11": 10,
      "score12": 10,
      "score21": 10,
      "score22": 10,
      "score31": 10,
      "score32": 10,
      "score41": 10,
      "score42": 10,
      "score51": 10,
      "score52": 10,
      "score61": 10,
      "score62": 10,
      "score71": 10,
      "score72": 10,
      "score81": 10,
      "score82": 10,
      "score91": 10,
      "score92": 10,
      "score101": 10,
      "score102": 10,
      "score111": 10,
      "score112": 10,
      "score121": 10,
      "score122": 10,
      "score131": 10,
      "score132": 10,
      "score141": 10,
      "score142": 10,
      "score151": 10,
      "score152": 10,
      "score161": 10,
      "score162": 10,
      "score171": 10,
      "score172": 10,
      "score181": 10,
      "score182": 10,
      "score191": 10,
      "score192": 10,
      "score201": 190,
      "score202": 190
    },
    {
      "name": "监督20",
      "score11": 10,
      "score12": 10,
      "score21": 10,
      "score22": 10,
      "score31": 10,
      "score32": 10,
      "score41": 10,
      "score42": 10,
      "score51": 10,
      "score52": 10,
      "score61": 10,
      "score62": 10,
      "score71": 10,
      "score72": 10,
      "score81": 10,
      "score82": 10,
      "score91": 10,
      "score92": 10,
      "score101": 10,
      "score102": 10,
      "score111": 10,
      "score112": 10,
      "score121": 10,
      "score122": 10,
      "score131": 10,
      "score132": 10,
      "score141": 10,
      "score142": 10,
      "score151": 10,
      "score152": 10,
      "score161": 10,
      "score162": 10,
      "score171": 10,
      "score172": 10,
      "score181": 10,
      "score182": 10,
      "score191": 10,
      "score192": 10,
      "score201": 190,
      "score202": 190
    },
    {
      "name": "监督21",
      "score11": 10,
      "score12": 10,
      "score21": 10,
      "score22": 10,
      "score31": 10,
      "score32": 10,
      "score41": 10,
      "score42": 10,
      "score51": 10,
      "score52": 10,
      "score61": 10,
      "score62": 10,
      "score71": 10,
      "score72": 10,
      "score81": 10,
      "score82": 10,
      "score91": 10,
      "score92": 10,
      "score101": 10,
      "score102": 10,
      "score111": 10,
      "score112": 10,
      "score121": 10,
      "score122": 10,
      "score131": 10,
      "score132": 10,
      "score141": 10,
      "score142": 10,
      "score151": 10,
      "score152": 10,
      "score161": 10,
      "score162": 10,
      "score171": 10,
      "score172": 10,
      "score181": 10,
      "score182": 10,
      "score191": 10,
      "score192": 10,
      "score201": 190,
      "score202": 190
    },
    {
      "name": "监督22",
      "score11": 10,
      "score12": 10,
      "score21": 10,
      "score22": 10,
      "score31": 10,
      "score32": 10,
      "score41": 10,
      "score42": 10,
      "score51": 10,
      "score52": 10,
      "score61": 10,
      "score62": 10,
      "score71": 10,
      "score72": 10,
      "score81": 10,
      "score82": 10,
      "score91": 10,
      "score92": 10,
      "score101": 10,
      "score102": 10,
      "score111": 10,
      "score112": 10,
      "score121": 10,
      "score122": 10,
      "score131": 10,
      "score132": 10,
      "score141": 10,
      "score142": 10,
      "score151": 10,
      "score152": 10,
      "score161": 10,
      "score162": 10,
      "score171": 10,
      "score172": 10,
      "score181": 10,
      "score182": 10,
      "score191": 10,
      "score192": 10,
      "score201": 190,
      "score202": 190
    },
    {
      "name": "监督23",
      "score11": 10,
      "score12": 10,
      "score21": 10,
      "score22": 10,
      "score31": 10,
      "score32": 10,
      "score41": 10,
      "score42": 10,
      "score51": 10,
      "score52": 10,
      "score61": 10,
      "score62": 10,
      "score71": 10,
      "score72": 10,
      "score81": 10,
      "score82": 10,
      "score91": 10,
      "score92": 10,
      "score101": 10,
      "score102": 10,
      "score111": 10,
      "score112": 10,
      "score121": 10,
      "score122": 10,
      "score131": 10,
      "score132": 10,
      "score141": 10,
      "score142": 10,
      "score151": 10,
      "score152": 10,
      "score161": 10,
      "score162": 10,
      "score171": 10,
      "score172": 10,
      "score181": 10,
      "score182": 10,
      "score191": 10,
      "score192": 10,
      "score201": 190,
      "score202": 190
    },
    {
      "name": "监督24",
      "score11": 10,
      "score12": 10,
      "score21": 10,
      "score22": 10,
      "score31": 10,
      "score32": 10,
      "score41": 10,
      "score42": 10,
      "score51": 10,
      "score52": 10,
      "score61": 10,
      "score62": 10,
      "score71": 10,
      "score72": 10,
      "score81": 10,
      "score82": 10,
      "score91": 10,
      "score92": 10,
      "score101": 10,
      "score102": 10,
      "score111": 10,
      "score112": 10,
      "score121": 10,
      "score122": 10,
      "score131": 10,
      "score132": 10,
      "score141": 10,
      "score142": 10,
      "score151": 10,
      "score152": 10,
      "score161": 10,
      "score162": 10,
      "score171": 10,
      "score172": 10,
      "score181": 10,
      "score182": 10,
      "score191": 10,
      "score192": 10,
      "score201": 190,
      "score202": 190
    },
    {
      "name": "监督25",
      "score11": 10,
      "score12": 10,
      "score21": 10,
      "score22": 10,
      "score31": 10,
      "score32": 10,
      "score41": 10,
      "score42": 10,
      "score51": 10,
      "score52": 10,
      "score61": 10,
      "score62": 10,
      "score71": 10,
      "score72": 10,
      "score81": 10,
      "score82": 10,
      "score91": 10,
      "score92": 10,
      "score101": 10,
      "score102": 10,
      "score111": 10,
      "score112": 10,
      "score121": 10,
      "score122": 10,
      "score131": 10,
      "score132": 10,
      "score141": 10,
      "score142": 10,
      "score151": 10,
      "score152": 10,
      "score161": 10,
      "score162": 10,
      "score171": 10,
      "score172": 10,
      "score181": 10,
      "score182": 10,
      "score191": 10,
      "score192": 10,
      "score201": 190,
      "score202": 190
    },
    {
      "name": "监督26",
      "score11": 10,
      "score12": 10,
      "score21": 10,
      "score22": 10,
      "score31": 10,
      "score32": 10,
      "score41": 10,
      "score42": 10,
      "score51": 10,
      "score52": 10,
      "score61": 10,
      "score62": 10,
      "score71": 10,
      "score72": 10,
      "score81": 10,
      "score82": 10,
      "score91": 10,
      "score92": 10,
      "score101": 10,
      "score102": 10,
      "score111": 10,
      "score112": 10,
      "score121": 10,
      "score122": 10,
      "score131": 10,
      "score132": 10,
      "score141": 10,
      "score142": 10,
      "score151": 10,
      "score152": 10,
      "score161": 10,
      "score162": 10,
      "score171": 10,
      "score172": 10,
      "score181": 10,
      "score182": 10,
      "score191": 10,
      "score192": 10,
      "score201": 190,
      "score202": 190
    },
    {
      "name": "监督27",
      "score11": 10,
      "score12": 10,
      "score21": 10,
      "score22": 10,
      "score31": 10,
      "score32": 10,
      "score41": 10,
      "score42": 10,
      "score51": 10,
      "score52": 10,
      "score61": 10,
      "score62": 10,
      "score71": 10,
      "score72": 10,
      "score81": 10,
      "score82": 10,
      "score91": 10,
      "score92": 10,
      "score101": 10,
      "score102": 10,
      "score111": 10,
      "score112": 10,
      "score121": 10,
      "score122": 10,
      "score131": 10,
      "score132": 10,
      "score141": 10,
      "score142": 10,
      "score151": 10,
      "score152": 10,
      "score161": 10,
      "score162": 10,
      "score171": 10,
      "score172": 10,
      "score181": 10,
      "score182": 10,
      "score191": 10,
      "score192": 10,
      "score201": 190,
      "score202": 190
    },
    {
      "name": "监督28",
      "score11": 10,
      "score12": 10,
      "score21": 10,
      "score22": 10,
      "score31": 10,
      "score32": 10,
      "score41": 10,
      "score42": 10,
      "score51": 10,
      "score52": 10,
      "score61": 10,
      "score62": 10,
      "score71": 10,
      "score72": 10,
      "score81": 10,
      "score82": 10,
      "score91": 10,
      "score92": 10,
      "score101": 10,
      "score102": 10,
      "score111": 10,
      "score112": 10,
      "score121": 10,
      "score122": 10,
      "score131": 10,
      "score132": 10,
      "score141": 10,
      "score142": 10,
      "score151": 10,
      "score152": 10,
      "score161": 10,
      "score162": 10,
      "score171": 10,
      "score172": 10,
      "score181": 10,
      "score182": 10,
      "score191": 10,
      "score192": 10,
      "score201": 190,
      "score202": 190
    },
    {
      "name": "监督29",
      "score11": 10,
      "score12": 10,
      "score21": 10,
      "score22": 10,
      "score31": 10,
      "score32": 10,
      "score41": 10,
      "score42": 10,
      "score51": 10,
      "score52": 10,
      "score61": 10,
      "score62": 10,
      "score71": 10,
      "score72": 10,
      "score81": 10,
      "score82": 10,
      "score91": 10,
      "score92": 10,
      "score101": 10,
      "score102": 10,
      "score111": 10,
      "score112": 10,
      "score121": 10,
      "score122": 10,
      "score131": 10,
      "score132": 10,
      "score141": 10,
      "score142": 10,
      "score151": 10,
      "score152": 10,
      "score161": 10,
      "score162": 10,
      "score171": 10,
      "score172": 10,
      "score181": 10,
      "score182": 10,
      "score191": 10,
      "score192": 10,
      "score201": 190,
      "score202": 190
    },
    {
      "name": "监督30",
      "score11": 10,
      "score12": 10,
      "score21": 10,
      "score22": 10,
      "score31": 10,
      "score32": 10,
      "score41": 10,
      "score42": 10,
      "score51": 10,
      "score52": 10,
      "score61": 10,
      "score62": 10,
      "score71": 10,
      "score72": 10,
      "score81": 10,
      "score82": 10,
      "score91": 10,
      "score92": 10,
      "score101": 10,
      "score102": 10,
      "score111": 10,
      "score112": 10,
      "score121": 10,
      "score122": 10,
      "score131": 10,
      "score132": 10,
      "score141": 10,
      "score142": 10,
      "score151": 10,
      "score152": 10,
      "score161": 10,
      "score162": 10,
      "score171": 10,
      "score172": 10,
      "score181": 10,
      "score182": 10,
      "score191": 10,
      "score192": 10,
      "score201": 190,
      "score202": 190
    },
    {
      "name": "总计",
      "score11": 300,
      "score12": 300,
      "score21": 300,
      "score22": 300,
      "score31": 300,
      "score32": 300,
      "score41": 300,
      "score42": 300,
      "score51": 300,
      "score52": 300,
      "score61": 300,
      "score62": 300,
      "score71": 300,
      "score72": 300,
      "score81": 300,
      "score82": 300,
      "score91": 300,
      "score92": 300,
      "score101": 300,
      "score102": 300,
      "score111": 300,
      "score112": 300,
      "score121": 300,
      "score122": 300,
      "score131": 300,
      "score132": 300,
      "score141": 300,
      "score142": 300,
      "score151": 300,
      "score152": 300,
      "score161": 300,
      "score162": 300,
      "score171": 300,
      "score172": 300,
      "score181": 300,
      "score182": 300,
      "score191": 300,
      "score192": 300
    }
  ]
}